tensor_maximum_entropy/__init__.py
tensor_maximum_entropy/test_run.py
tensor_maximum_entropy/tme.py
tensor_maximum_entropy/utils.py
tensor_maximum_entropy-0.0.2.dist-info/LICENSE.txt
tensor_maximum_entropy-0.0.2.dist-info/METADATA
tensor_maximum_entropy-0.0.2.dist-info/WHEEL
tensor_maximum_entropy-0.0.2.dist-info/top_level.txt
tensor_maximum_entropy-0.0.2.dist-info/RECORD
