Metadata-Version: 2.1
Name: tensor-maximum-entropy
Version: 0.0.2
Summary: Python implementation of the Tensor Maximum Entropy (TME)
Home-page: https://github.com/ArdeleanRichard/TME
Author: Eugen-Richard Ardelean
Author-email: ardeleaneugenrichard@gmail.com
License: MIT
Classifier: License :: OSI Approved :: MIT License
Classifier: Programming Language :: Python :: 3.7
Classifier: Operating System :: OS Independent
Requires-Python: >=3.7
License-File: LICENSE.txt
Requires-Dist: numpy
Requires-Dist: scipy
Requires-Dist: matplotlib
Requires-Dist: scikit-learn
Provides-Extra: dev
Requires-Dist: twine >=4.0.2 ; extra == 'dev'
